{
    "eval_loss": 4.428328990936279,
    "eval_accuracy": 0.8872549019607843,
    "eval_f1": 0.9209621993127148,
    "eval_runtime": 0.1212,
    "eval_samples_per_second": 3366.858,
    "eval_steps_per_second": 33.008,
    "epoch": 89.65517241379311,
    "log_history": [
        {
            "loss": 1.4676,
            "grad_norm": 2.3838396072387695,
            "learning_rate": 6.896551724137931e-05,
            "epoch": 6.896551724137931,
            "step": 200
        },
        {
            "eval_loss": 1.61173677444458,
            "eval_accuracy": 0.8161764705882353,
            "eval_f1": 0.8743718592964823,
            "eval_runtime": 0.105,
            "eval_samples_per_second": 3884.302,
            "eval_steps_per_second": 38.081,
            "epoch": 6.896551724137931,
            "step": 200
        },
        {
            "loss": 0.7743,
            "grad_norm": 6.478668212890625,
            "learning_rate": 9.578544061302682e-05,
            "epoch": 13.793103448275861,
            "step": 400
        },
        {
            "eval_loss": 2.6213762760162354,
            "eval_accuracy": 0.8823529411764706,
            "eval_f1": 0.9163763066202091,
            "eval_runtime": 0.1041,
            "eval_samples_per_second": 3917.649,
            "eval_steps_per_second": 38.408,
            "epoch": 13.793103448275861,
            "step": 400
        },
        {
            "loss": 0.4025,
            "grad_norm": 6.235653877258301,
            "learning_rate": 8.812260536398468e-05,
            "epoch": 20.689655172413794,
            "step": 600
        },
        {
            "eval_loss": 3.3062148094177246,
            "eval_accuracy": 0.875,
            "eval_f1": 0.9103690685413005,
            "eval_runtime": 0.1228,
            "eval_samples_per_second": 3322.802,
            "eval_steps_per_second": 32.576,
            "epoch": 20.689655172413794,
            "step": 600
        },
        {
            "loss": 0.24,
            "grad_norm": 3.292679786682129,
            "learning_rate": 8.045977011494253e-05,
            "epoch": 27.586206896551722,
            "step": 800
        },
        {
            "eval_loss": 3.6044914722442627,
            "eval_accuracy": 0.8823529411764706,
            "eval_f1": 0.9183673469387754,
            "eval_runtime": 0.1034,
            "eval_samples_per_second": 3945.041,
            "eval_steps_per_second": 38.677,
            "epoch": 27.586206896551722,
            "step": 800
        },
        {
            "loss": 0.1671,
            "grad_norm": 1.50715970993042,
            "learning_rate": 7.279693486590039e-05,
            "epoch": 34.48275862068966,
            "step": 1000
        },
        {
            "eval_loss": 3.8648037910461426,
            "eval_accuracy": 0.8848039215686274,
            "eval_f1": 0.9196581196581197,
            "eval_runtime": 0.1039,
            "eval_samples_per_second": 3925.431,
            "eval_steps_per_second": 38.485,
            "epoch": 34.48275862068966,
            "step": 1000
        },
        {
            "loss": 0.1219,
            "grad_norm": 13.460265159606934,
            "learning_rate": 6.513409961685824e-05,
            "epoch": 41.37931034482759,
            "step": 1200
        },
        {
            "eval_loss": 4.379907131195068,
            "eval_accuracy": 0.8823529411764706,
            "eval_f1": 0.9145907473309609,
            "eval_runtime": 0.1034,
            "eval_samples_per_second": 3944.568,
            "eval_steps_per_second": 38.672,
            "epoch": 41.37931034482759,
            "step": 1200
        },
        {
            "loss": 0.0895,
            "grad_norm": 1.274167537689209,
            "learning_rate": 5.747126436781609e-05,
            "epoch": 48.275862068965516,
            "step": 1400
        },
        {
            "eval_loss": 4.396983623504639,
            "eval_accuracy": 0.8823529411764706,
            "eval_f1": 0.9175257731958764,
            "eval_runtime": 0.1029,
            "eval_samples_per_second": 3966.806,
            "eval_steps_per_second": 38.89,
            "epoch": 48.275862068965516,
            "step": 1400
        },
        {
            "loss": 0.0757,
            "grad_norm": 0.8028013706207275,
            "learning_rate": 4.980842911877395e-05,
            "epoch": 55.172413793103445,
            "step": 1600
        },
        {
            "eval_loss": 4.428328990936279,
            "eval_accuracy": 0.8872549019607843,
            "eval_f1": 0.9209621993127148,
            "eval_runtime": 0.1049,
            "eval_samples_per_second": 3889.83,
            "eval_steps_per_second": 38.136,
            "epoch": 55.172413793103445,
            "step": 1600
        },
        {
            "loss": 0.0525,
            "grad_norm": 5.501101493835449,
            "learning_rate": 4.21455938697318e-05,
            "epoch": 62.06896551724138,
            "step": 1800
        },
        {
            "eval_loss": 4.527716636657715,
            "eval_accuracy": 0.875,
            "eval_f1": 0.9125214408233276,
            "eval_runtime": 0.1194,
            "eval_samples_per_second": 3415.973,
            "eval_steps_per_second": 33.49,
            "epoch": 62.06896551724138,
            "step": 1800
        },
        {
            "loss": 0.0412,
            "grad_norm": 7.1729254722595215,
            "learning_rate": 3.4482758620689657e-05,
            "epoch": 68.96551724137932,
            "step": 2000
        },
        {
            "eval_loss": 4.703088760375977,
            "eval_accuracy": 0.8872549019607843,
            "eval_f1": 0.9198606271777002,
            "eval_runtime": 0.1205,
            "eval_samples_per_second": 3386.895,
            "eval_steps_per_second": 33.205,
            "epoch": 68.96551724137932,
            "step": 2000
        },
        {
            "loss": 0.0358,
            "grad_norm": 4.6350626945495605,
            "learning_rate": 2.681992337164751e-05,
            "epoch": 75.86206896551724,
            "step": 2200
        },
        {
            "eval_loss": 4.625133514404297,
            "eval_accuracy": 0.8774509803921569,
            "eval_f1": 0.9146757679180888,
            "eval_runtime": 0.1188,
            "eval_samples_per_second": 3433.457,
            "eval_steps_per_second": 33.661,
            "epoch": 75.86206896551724,
            "step": 2200
        },
        {
            "loss": 0.0308,
            "grad_norm": 0.30784496665000916,
            "learning_rate": 1.9157088122605367e-05,
            "epoch": 82.75862068965517,
            "step": 2400
        },
        {
            "eval_loss": 4.719411849975586,
            "eval_accuracy": 0.875,
            "eval_f1": 0.9116117850953207,
            "eval_runtime": 0.1038,
            "eval_samples_per_second": 3929.217,
            "eval_steps_per_second": 38.522,
            "epoch": 82.75862068965517,
            "step": 2400
        },
        {
            "loss": 0.0246,
            "grad_norm": 0.04468488320708275,
            "learning_rate": 1.1494252873563218e-05,
            "epoch": 89.65517241379311,
            "step": 2600
        },
        {
            "eval_loss": 4.744435787200928,
            "eval_accuracy": 0.875,
            "eval_f1": 0.9122203098106711,
            "eval_runtime": 0.1202,
            "eval_samples_per_second": 3393.571,
            "eval_steps_per_second": 33.27,
            "epoch": 89.65517241379311,
            "step": 2600
        },
        {
            "train_runtime": 159.1174,
            "train_samples_per_second": 2305.215,
            "train_steps_per_second": 18.226,
            "total_flos": 1.1323579807301632e+16,
            "train_loss": 0.27104712119469276,
            "epoch": 89.65517241379311,
            "step": 2600
        },
        {
            "eval_loss": 4.428328990936279,
            "eval_accuracy": 0.8872549019607843,
            "eval_f1": 0.9209621993127148,
            "eval_runtime": 0.1212,
            "eval_samples_per_second": 3366.858,
            "eval_steps_per_second": 33.008,
            "epoch": 89.65517241379311,
            "step": 2600
        }
    ],
    "args": {
        "dataset_path": "./dataset",
        "train_batch_size": 32,
        "eval_batch_size": 32,
        "weight_decay": 0.01,
        "dir_name": "./results",
        "use_rslora": false,
        "teacher_learning_rate": 2e-05,
        "student_learning_rate": 0.0001,
        "lora_learning_rate": 0.0002,
        "num_train_epochs": 100,
        "peft": "olora",
        "rank": 64,
        "lora_alpha": 64,
        "lora_dropout": 0.05,
        "type": 1,
        "model_family": "deberta",
        "task": "mrpc",
        "seed": 999,
        "student_model_name": "./models/deberta-v3-small",
        "teacher_model_name": "./models/deberta-v3-base",
        "train_size": 3668
    },
    "train": {
        "train_time": 159.1174,
        "trainable_params_count": 1.181186,
        "memory_allocated": [
            604.892672,
            604.892672,
            604.892672,
            604.892672,
            604.892672,
            604.892672,
            604.892672,
            604.892672,
            604.892672,
            604.892672,
            604.892672,
            604.892672,
            604.892672,
            604.892672,
            604.892672,
            604.892672,
            604.892672,
            604.892672,
            604.892672,
            604.892672,
            604.892672,
            604.892672,
            604.892672,
            604.892672,
            604.892672,
            604.892672,
            604.892672,
            604.892672,
            604.892672,
            604.892672,
            604.892672,
            604.892672,
            604.892672,
            604.892672,
            604.892672,
            604.892672,
            604.892672,
            604.892672,
            604.892672,
            604.892672,
            604.892672,
            604.892672,
            604.892672,
            604.892672,
            604.892672,
            604.892672,
            604.892672,
            604.892672,
            604.892672,
            604.892672,
            604.892672,
            604.892672,
            604.892672,
            604.892672,
            604.892672,
            604.892672,
            604.892672,
            604.892672,
            604.892672,
            604.892672,
            604.892672,
            604.892672,
            604.892672,
            604.892672,
            604.892672,
            604.892672,
            604.892672,
            604.892672,
            604.892672,
            604.892672,
            604.892672,
            604.892672,
            604.892672,
            604.892672,
            604.892672,
            604.892672,
            604.892672,
            604.892672,
            604.892672,
            604.892672,
            604.892672,
            604.892672,
            604.892672,
            604.892672,
            604.892672,
            604.892672,
            604.892672,
            604.892672,
            604.892672,
            604.892672
        ],
        "memory_reserved": [
            2657.091584,
            2657.091584,
            2657.091584,
            2657.091584,
            2657.091584,
            2657.091584,
            2657.091584,
            2657.091584,
            2657.091584,
            2657.091584,
            2657.091584,
            2657.091584,
            2657.091584,
            2657.091584,
            2657.091584,
            2657.091584,
            2657.091584,
            2657.091584,
            2657.091584,
            2657.091584,
            2657.091584,
            2657.091584,
            2657.091584,
            2657.091584,
            2657.091584,
            2657.091584,
            2657.091584,
            2657.091584,
            2657.091584,
            2657.091584,
            2657.091584,
            2657.091584,
            2657.091584,
            2657.091584,
            2657.091584,
            2657.091584,
            2657.091584,
            2657.091584,
            2657.091584,
            2657.091584,
            2657.091584,
            2657.091584,
            2657.091584,
            2657.091584,
            2657.091584,
            2657.091584,
            2657.091584,
            2657.091584,
            2657.091584,
            2657.091584,
            2657.091584,
            2657.091584,
            2657.091584,
            2657.091584,
            2657.091584,
            2657.091584,
            2657.091584,
            2657.091584,
            2657.091584,
            2657.091584,
            2657.091584,
            2657.091584,
            2657.091584,
            2657.091584,
            2657.091584,
            2657.091584,
            2657.091584,
            2657.091584,
            2657.091584,
            2657.091584,
            2657.091584,
            2657.091584,
            2657.091584,
            2657.091584,
            2657.091584,
            2657.091584,
            2657.091584,
            2657.091584,
            2657.091584,
            2657.091584,
            2657.091584,
            2657.091584,
            2657.091584,
            2657.091584,
            2657.091584,
            2657.091584,
            2657.091584,
            2657.091584,
            2657.091584,
            2657.091584
        ]
    },
    "variant": "kd-lora"
}