{
    "eval_loss": 0.7918307781219482,
    "eval_matthews_correlation": 0.38243251431807235,
    "eval_runtime": 0.2003,
    "eval_samples_per_second": 5208.281,
    "eval_steps_per_second": 44.942,
    "epoch": 3.0,
    "log_history": [
        {
            "loss": 0.7332,
            "grad_norm": 0.8915639519691467,
            "learning_rate": 9.502487562189055e-05,
            "epoch": 0.14925373134328357,
            "step": 10
        },
        {
            "eval_loss": 0.6297421455383301,
            "eval_matthews_correlation": 0.0,
            "eval_runtime": 0.2942,
            "eval_samples_per_second": 3545.725,
            "eval_steps_per_second": 30.596,
            "epoch": 0.14925373134328357,
            "step": 10
        },
        {
            "loss": 0.6576,
            "grad_norm": 1.0524497032165527,
            "learning_rate": 9.00497512437811e-05,
            "epoch": 0.29850746268656714,
            "step": 20
        },
        {
            "eval_loss": 0.6474553346633911,
            "eval_matthews_correlation": 0.0,
            "eval_runtime": 0.2826,
            "eval_samples_per_second": 3690.861,
            "eval_steps_per_second": 31.848,
            "epoch": 0.29850746268656714,
            "step": 20
        },
        {
            "loss": 0.6491,
            "grad_norm": 0.49095457792282104,
            "learning_rate": 8.507462686567164e-05,
            "epoch": 0.44776119402985076,
            "step": 30
        },
        {
            "eval_loss": 0.6247731447219849,
            "eval_matthews_correlation": 0.0,
            "eval_runtime": 0.2999,
            "eval_samples_per_second": 3477.56,
            "eval_steps_per_second": 30.008,
            "epoch": 0.44776119402985076,
            "step": 30
        },
        {
            "loss": 0.6039,
            "grad_norm": 0.5679992437362671,
            "learning_rate": 8.00995024875622e-05,
            "epoch": 0.5970149253731343,
            "step": 40
        },
        {
            "eval_loss": 0.6373358964920044,
            "eval_matthews_correlation": 0.0,
            "eval_runtime": 0.2868,
            "eval_samples_per_second": 3636.821,
            "eval_steps_per_second": 31.382,
            "epoch": 0.5970149253731343,
            "step": 40
        },
        {
            "loss": 0.6478,
            "grad_norm": 1.1942880153656006,
            "learning_rate": 7.512437810945275e-05,
            "epoch": 0.746268656716418,
            "step": 50
        },
        {
            "eval_loss": 0.6244940161705017,
            "eval_matthews_correlation": 0.0,
            "eval_runtime": 0.2859,
            "eval_samples_per_second": 3648.015,
            "eval_steps_per_second": 31.479,
            "epoch": 0.746268656716418,
            "step": 50
        },
        {
            "loss": 0.6318,
            "grad_norm": 0.8130281567573547,
            "learning_rate": 7.014925373134329e-05,
            "epoch": 0.8955223880597015,
            "step": 60
        },
        {
            "eval_loss": 0.6164695024490356,
            "eval_matthews_correlation": 0.0,
            "eval_runtime": 0.2803,
            "eval_samples_per_second": 3720.66,
            "eval_steps_per_second": 32.105,
            "epoch": 0.8955223880597015,
            "step": 60
        },
        {
            "loss": 0.5901,
            "grad_norm": 1.843998670578003,
            "learning_rate": 6.517412935323384e-05,
            "epoch": 1.044776119402985,
            "step": 70
        },
        {
            "eval_loss": 0.6498405337333679,
            "eval_matthews_correlation": 0.0,
            "eval_runtime": 0.3144,
            "eval_samples_per_second": 3317.773,
            "eval_steps_per_second": 28.629,
            "epoch": 1.044776119402985,
            "step": 70
        },
        {
            "loss": 0.5548,
            "grad_norm": 2.712259531021118,
            "learning_rate": 6.019900497512438e-05,
            "epoch": 1.1940298507462686,
            "step": 80
        },
        {
            "eval_loss": 0.640684962272644,
            "eval_matthews_correlation": 0.14722770277531896,
            "eval_runtime": 0.2281,
            "eval_samples_per_second": 4572.526,
            "eval_steps_per_second": 39.456,
            "epoch": 1.1940298507462686,
            "step": 80
        },
        {
            "loss": 0.5173,
            "grad_norm": 2.1045470237731934,
            "learning_rate": 5.5223880597014934e-05,
            "epoch": 1.3432835820895521,
            "step": 90
        },
        {
            "eval_loss": 0.7004378437995911,
            "eval_matthews_correlation": 0.2247002360444496,
            "eval_runtime": 0.2231,
            "eval_samples_per_second": 4675.939,
            "eval_steps_per_second": 40.348,
            "epoch": 1.3432835820895521,
            "step": 90
        },
        {
            "loss": 0.5133,
            "grad_norm": 3.5203781127929688,
            "learning_rate": 5.024875621890548e-05,
            "epoch": 1.4925373134328357,
            "step": 100
        },
        {
            "eval_loss": 0.7328363060951233,
            "eval_matthews_correlation": 0.33166750313166415,
            "eval_runtime": 0.208,
            "eval_samples_per_second": 5015.189,
            "eval_steps_per_second": 43.276,
            "epoch": 1.4925373134328357,
            "step": 100
        },
        {
            "loss": 0.5183,
            "grad_norm": 7.730218887329102,
            "learning_rate": 4.5273631840796025e-05,
            "epoch": 1.6417910447761193,
            "step": 110
        },
        {
            "eval_loss": 0.7761014699935913,
            "eval_matthews_correlation": 0.359676506219852,
            "eval_runtime": 0.2216,
            "eval_samples_per_second": 4706.298,
            "eval_steps_per_second": 40.61,
            "epoch": 1.6417910447761193,
            "step": 110
        },
        {
            "loss": 0.4952,
            "grad_norm": 5.9385905265808105,
            "learning_rate": 4.029850746268657e-05,
            "epoch": 1.7910447761194028,
            "step": 120
        },
        {
            "eval_loss": 0.7742957472801208,
            "eval_matthews_correlation": 0.3791372485356886,
            "eval_runtime": 0.2755,
            "eval_samples_per_second": 3785.578,
            "eval_steps_per_second": 32.666,
            "epoch": 1.7910447761194028,
            "step": 120
        },
        {
            "loss": 0.4601,
            "grad_norm": 2.6274027824401855,
            "learning_rate": 3.5323383084577115e-05,
            "epoch": 1.9402985074626866,
            "step": 130
        },
        {
            "eval_loss": 0.7983077764511108,
            "eval_matthews_correlation": 0.362292826673941,
            "eval_runtime": 0.2795,
            "eval_samples_per_second": 3732.16,
            "eval_steps_per_second": 32.205,
            "epoch": 1.9402985074626866,
            "step": 130
        },
        {
            "loss": 0.471,
            "grad_norm": 3.09885311126709,
            "learning_rate": 3.0348258706467664e-05,
            "epoch": 2.08955223880597,
            "step": 140
        },
        {
            "eval_loss": 0.7859801054000854,
            "eval_matthews_correlation": 0.36514812386282536,
            "eval_runtime": 0.311,
            "eval_samples_per_second": 3354.023,
            "eval_steps_per_second": 28.942,
            "epoch": 2.08955223880597,
            "step": 140
        },
        {
            "loss": 0.4663,
            "grad_norm": 4.73264741897583,
            "learning_rate": 2.537313432835821e-05,
            "epoch": 2.2388059701492535,
            "step": 150
        },
        {
            "eval_loss": 0.7588246464729309,
            "eval_matthews_correlation": 0.3885708666744343,
            "eval_runtime": 0.2587,
            "eval_samples_per_second": 4031.944,
            "eval_steps_per_second": 34.791,
            "epoch": 2.2388059701492535,
            "step": 150
        },
        {
            "loss": 0.4672,
            "grad_norm": 3.4282121658325195,
            "learning_rate": 2.0398009950248755e-05,
            "epoch": 2.388059701492537,
            "step": 160
        },
        {
            "eval_loss": 0.7699321508407593,
            "eval_matthews_correlation": 0.38871572576733826,
            "eval_runtime": 0.2907,
            "eval_samples_per_second": 3587.901,
            "eval_steps_per_second": 30.96,
            "epoch": 2.388059701492537,
            "step": 160
        },
        {
            "loss": 0.4575,
            "grad_norm": 7.267443656921387,
            "learning_rate": 1.5422885572139304e-05,
            "epoch": 2.5373134328358207,
            "step": 170
        },
        {
            "eval_loss": 0.7978546023368835,
            "eval_matthews_correlation": 0.3825675441068272,
            "eval_runtime": 0.2684,
            "eval_samples_per_second": 3885.436,
            "eval_steps_per_second": 33.527,
            "epoch": 2.5373134328358207,
            "step": 170
        },
        {
            "loss": 0.4658,
            "grad_norm": 2.8054606914520264,
            "learning_rate": 1.0447761194029851e-05,
            "epoch": 2.6865671641791042,
            "step": 180
        },
        {
            "eval_loss": 0.7827627062797546,
            "eval_matthews_correlation": 0.39162119073448115,
            "eval_runtime": 0.2792,
            "eval_samples_per_second": 3736.17,
            "eval_steps_per_second": 32.239,
            "epoch": 2.6865671641791042,
            "step": 180
        },
        {
            "loss": 0.4236,
            "grad_norm": 2.2804019451141357,
            "learning_rate": 5.472636815920398e-06,
            "epoch": 2.835820895522388,
            "step": 190
        },
        {
            "eval_loss": 0.7867456078529358,
            "eval_matthews_correlation": 0.3885708666744343,
            "eval_runtime": 0.2701,
            "eval_samples_per_second": 3861.391,
            "eval_steps_per_second": 33.32,
            "epoch": 2.835820895522388,
            "step": 190
        },
        {
            "loss": 0.4494,
            "grad_norm": 3.2044484615325928,
            "learning_rate": 4.975124378109453e-07,
            "epoch": 2.9850746268656714,
            "step": 200
        },
        {
            "eval_loss": 0.7927601933479309,
            "eval_matthews_correlation": 0.38243251431807235,
            "eval_runtime": 0.2238,
            "eval_samples_per_second": 4659.598,
            "eval_steps_per_second": 40.207,
            "epoch": 2.9850746268656714,
            "step": 200
        },
        {
            "train_runtime": 20.3835,
            "train_samples_per_second": 1258.517,
            "train_steps_per_second": 9.861,
            "total_flos": 864823376609280.0,
            "train_loss": 0.5384527972681605,
            "epoch": 3.0,
            "step": 201
        },
        {
            "eval_loss": 0.7918307781219482,
            "eval_matthews_correlation": 0.38243251431807235,
            "eval_runtime": 0.2003,
            "eval_samples_per_second": 5208.281,
            "eval_steps_per_second": 44.942,
            "epoch": 3.0,
            "step": 201
        }
    ],
    "args": {
        "teacher_model_name": "./models/roberta-base",
        "student_model_name": "./models/distilroberta-base",
        "dataset_path": "./dataset",
        "train_batch_size": 32,
        "eval_batch_size": 32,
        "num_train_epochs": 3,
        "weight_decay": 0.01,
        "dir_name": "./converge",
        "rank": 4,
        "lora_alpha": 16,
        "lora_dropout": 0.05,
        "use_rslora": true,
        "teacher_learning_rate": 5e-05,
        "student_learning_rate": 0.0001,
        "task": "cola",
        "peft": "mrlora-rs",
        "seed": 42,
        "type": 1,
        "from_disk": 1,
        "model_family": "roberta",
        "train_size": 8551
    },
    "train": {
        "train_time": 20.3835,
        "trainable_params_count": 0.64745,
        "memory_allocated": [
            356.365824,
            356.365824,
            356.365824
        ],
        "memory_reserved": [
            1413.480448,
            1413.480448,
            1413.480448
        ]
    },
    "variant": "kd-lora"
}